ipcvexx/__init__.py
ipcvexx/bccd.py
ipcvexx/canny.py
ipcvexx/coco.py
ipcvexx/coco2.py
ipcvexx/hog.py
ipcvexx/horse.py
ipcvexx/img.py
ipcvexx/sift.py
ipcvexx-0.1.0.dist-info/METADATA
ipcvexx-0.1.0.dist-info/WHEEL
ipcvexx-0.1.0.dist-info/top_level.txt
ipcvexx-0.1.0.dist-info/RECORD
