Metadata-Version: 2.4
Name: ipcvexx
Version: 0.1.0
Summary: A simple example package
Author-email: Your Name <you@example.com>
License: MIT
Requires-Dist: pandas
Requires-Dist: numpy
Requires-Dist: scikit-learn
Requires-Dist: matplotlib
